gps_tracker/__init__.py
gps_tracker/_version.py
gps_tracker/py.typed
gps_tracker/client/__init__.py
gps_tracker/client/asynchronous.py
gps_tracker/client/config.py
gps_tracker/client/datatypes.py
gps_tracker/client/exceptions.py
gps_tracker/client/synchronous.py
gps_tracker/client/url_provider.py
gps_tracker-0.9.0.dist-info/WHEEL
gps_tracker-0.9.0.dist-info/METADATA
gps_tracker-0.9.0.dist-info/RECORD
