Metadata-Version: 2.1
Name: gps_tracker
Version: 0.9.0
Summary: Unofficial client to retrieve location data from Invoxia™ GPS trackers.
Author-email: Ezlo Picori <ezlo@protonmail.com>
Requires-Python: >=3.8
Classifier: Development Status :: 4 - Beta
Classifier: License :: OSI Approved :: MIT License
Classifier: Natural Language :: English
Classifier: Programming Language :: Python
Classifier: Programming Language :: Python :: 3.9
Classifier: Programming Language :: Python :: 3.10
Requires-Dist: aiohttp
Requires-Dist: attrs
Requires-Dist: requests
Requires-Dist: aioresponses ; extra == "dev"
Requires-Dist: mypy ; extra == "dev"
Requires-Dist: pre-commit ; extra == "dev"
Requires-Dist: pylint ; extra == "dev"
Requires-Dist: pytest ; extra == "dev"
Requires-Dist: pytest-asyncio ; extra == "dev"
Requires-Dist: pytest-cov ; extra == "dev"
Requires-Dist: pytest-socket ; extra == "dev"
Requires-Dist: requests-mock ; extra == "dev"
Requires-Dist: setuptools ; extra == "dev"
Requires-Dist: tox ; extra == "dev"
Project-URL: Changelog, https://gps_tracker.readthedocs.io/en/latest/changelog.html
Project-URL: Documentation, https://gps_tracker.readthedocs.io/
Project-URL: Download, https://pypi.org/project/gps_tracker/#files
Project-URL: Homepage, https://gitlab.com/ezlo.picori/gps_tracker
Project-URL: Source, https://gitlab.com/ezlo.picori/gps_tracker
Project-URL: Tracker, https://gitlab.com/ezlo.picori/gps_tracker/-/issues
Provides-Extra: dev
